convexml/__init__.py
convexml/_branch_length_estimator.py
convexml/_convexml.py
convexml/_iid_exponential_mle.py
convexml/_multifurcations.py
convexml/_parsimony.py
convexml/_plot_tree.py
convexml/_utils.py
convexml-1.0.0.dist-info/licenses/LICENSE
convexml-1.0.0.dist-info/METADATA
convexml-1.0.0.dist-info/WHEEL
convexml-1.0.0.dist-info/top_level.txt
convexml-1.0.0.dist-info/RECORD
