Metadata-Version: 2.4
Name: convexml
Version: 1.0.0
Summary: ConvexML: Branch length estimation under irreversible mutation models.
Author: Sebastian Prillo
License: BSD-3-Clause
Requires-Python: >=3.10
License-File: LICENSE
Requires-Dist: cassiopeia-lineage
Requires-Dist: cvxpy
Requires-Dist: networkx
Requires-Dist: numpy
Dynamic: license-file
